{
  "event_type": "gala dinner",
  "price_type": "per_person",
  "final_price_value": 7125,
  "min_guests": 50,
  "max_guests": 200,
  "includes_vat": false,
  "is_kosher": true,
  "kosher_supervision": "local Orthodox rabbi",
  "includes_bar": true,
  "menu_type": "mixed",
  "dietary_options": [
    "vegetarian"
  ],
  "event_date": "2023-11-15",
  "cancellation_policy": "cancellations up to two weeks prior to the event with a full refund",
  "menu_highlights": [
    "roasted chicken",
    "seasonal vegetables",
    "gourmet desserts"
  ],
  "extra_notes": null
}