{
  "event_type": "charity gala",
  "price_type": "per_person",
  "final_price_value": 45,
  "min_guests": 200,
  "max_guests": 200,
  "includes_vat": true,
  "is_kosher": true,
  "kosher_supervision": "Orthodox Union",
  "includes_bar": true,
  "menu_type": "mixed",
  "dietary_options": [
    "vegetarian",
    "gluten-free"
  ],
  "event_date": "2023-04-15",
  "cancellation_policy": null,
  "menu_highlights": [
    "roasted chicken",
    "seasonal vegetable medley",
    "selection of desserts"
  ],
  "extra_notes": null
}