{
  "event_type": "corporate event",
  "price_type": "per person",
  "final_price_value": 2800,
  "min_guests": 50,
  "max_guests": 150,
  "includes_vat": true,
  "is_kosher": true,
  "kosher_supervision": "local Rabbinical council",
  "includes_bar": false,
  "menu_type": "mixed",
  "dietary_options": null,
  "event_date": "2023-11-15",
  "cancellation_policy": null,
  "menu_highlights": "herb-crusted chicken, roasted vegetables, gourmet salads, dessert bar",
  "extra_notes": null
}