{
  "event_type": "corporate gala",
  "price_type": "per_person",
  "final_price_value": 60,
  "min_guests": 100,
  "max_guests": 200,
  "includes_vat": true,
  "is_kosher": true,
  "kosher_supervision": "Orthodox Union",
  "includes_bar": true,
  "menu_type": "mixed",
  "dietary_options": [],
  "event_date": "2023-03-15",
  "cancellation_policy": null,
  "menu_highlights": [
    "herb-roasted chicken",
    "grilled vegetable platters",
    "gourmet desserts"
  ],
  "extra_notes": null
}